[{"content":"Разработчики MinIO, совместимого с Amazon S3 высокопроизводительного объектного хранилища, насчитывающего более миллиарда загрузок на Docker Hub, перевели Git-репозиторий проекта в архивный режим, допускающий доступ только для чтения. Последним изменением в репозитории стало добавление примечания о прекращении сопровождения и рекомендации перейти на проприетарный продукт MinIO AIStor. Архивирование стало финальным шагом в череде событий, которые восприняты сообществом как имитация открытости (Openwashing - использование репутации свободного проекта для продвижения проприетарного продукта).\nhttps://www.opennet.ru/opennews/art.shtml?num=64844\n","permalink":"https://ihadtoinstalllinux.github.io/posts/news/","summary":"Разработчики MinIO, совместимого с Amazon S3 высокопроизводительного объектного хранилища, насчитывающего более миллиарда загрузок на Docker Hub, перевели Git-репозиторий проекта в архивный режим, допускающий доступ только для чтения. Последним изменением в репозитории стало добавление примечания о прекращении сопровождения и рекомендации перейти на проприетарный продукт MinIO AIStor. Архивирование стало финальным шагом в череде событий, которые восприняты сообществом как имитация открытости (Openwashing - использование репутации свободного проекта для продвижения проприетарного продукта).\nhttps://www.opennet.ru/opennews/art.shtml?num=64844","title":"Проект MinIO перевёл Git-репозиторий в архивный режим. В ответ сообществом создан форк"},{"content":"vk: https://vk.com/ihadtoinstalllinux\ntelegram: https://t.me/ihadtoinstalllinux\n","permalink":"https://ihadtoinstalllinux.github.io/posts/about/","summary":"vk: https://vk.com/ihadtoinstalllinux\ntelegram: https://t.me/ihadtoinstalllinux","title":"About Us"}]