[{"content":"Кевин Кофлер (Kevin Kofler) из проекта Fedora, входящий в рабочую группу, занимающуюся сопровождением пакетов с KDE, объявил о формировании для Fedora пакетов с XLibre X Server, форком X.Org Server, нацеленным на активное развитие и проведение большой чистки X-сервера. Для использования с XLibre также подготовлены пакеты с совместимыми драйверами xorg-x11-drv-*.\nhttps://www.opennet.ru/opennews/art.shtml?num=63736\n","permalink":"https://ihadtoinstalllinux.github.io/posts/news/","summary":"Кевин Кофлер (Kevin Kofler) из проекта Fedora, входящий в рабочую группу, занимающуюся сопровождением пакетов с KDE, объявил о формировании для Fedora пакетов с XLibre X Server, форком X.Org Server, нацеленным на активное развитие и проведение большой чистки X-сервера. Для использования с XLibre также подготовлены пакеты с совместимыми драйверами xorg-x11-drv-*.\nhttps://www.opennet.ru/opennews/art.shtml?num=63736","title":"Для тестирования в Fedora предложены пакеты с альтернативным X-сервером XLibre"},{"content":"vk: https://vk.com/ihadtoinstalllinux\ntelegram: https://t.me/ihadtoinstalllinux\n","permalink":"https://ihadtoinstalllinux.github.io/posts/about/","summary":"vk: https://vk.com/ihadtoinstalllinux\ntelegram: https://t.me/ihadtoinstalllinux","title":"About Us"}]