[{"content":"В кодовую базу, которая будет использована в выпуске GNOME 49, принято изменение, отключающее по умолчанию сеанс X11 в дисплейном менеджере GDM (GNOME Display Manager), предоставляющем экран входа в систему. При сборке GDM также выставлена опция \u0026ldquo;-Dx11-support=false\u0026rdquo;, отключающая по умолчанию компиляцию компонентов для поддержки X11. Ведётся работа над возможностью собирать конфигуратор GNOME Setting без поддержки X11. Через год в выпуске GNOME 50 намерены полностью удалить из GNOME код для работы сеанса на базе X11.\nhttps://www.opennet.ru/opennews/art.shtml?num=63272\n","permalink":"https://ihadtoinstalllinux.github.io/posts/news/","summary":"В кодовую базу, которая будет использована в выпуске GNOME 49, принято изменение, отключающее по умолчанию сеанс X11 в дисплейном менеджере GDM (GNOME Display Manager), предоставляющем экран входа в систему. При сборке GDM также выставлена опция \u0026ldquo;-Dx11-support=false\u0026rdquo;, отключающая по умолчанию компиляцию компонентов для поддержки X11. Ведётся работа над возможностью собирать конфигуратор GNOME Setting без поддержки X11. Через год в выпуске GNOME 50 намерены полностью удалить из GNOME код для работы сеанса на базе X11.","title":"В GDM по умолчанию отключён сеанс X11. В Fedora 43 в GNOME будет поддерживаться только Wayland"},{"content":"vk: https://vk.com/ihadtoinstalllinux\ntelegram: https://t.me/ihadtoinstalllinux\n","permalink":"https://ihadtoinstalllinux.github.io/posts/about/","summary":"vk: https://vk.com/ihadtoinstalllinux\ntelegram: https://t.me/ihadtoinstalllinux","title":"About Us"}]