[{"content":"Каролина Стейдж (Caroline Stage), министр по цифровизации в правительстве Дании, подтвердила согласование между правительством и региональными властями стратегии цифрового суверенитета. На первом этапе воплощения новой стратегии в жизнь Министерство цифровизации Дании прекратит использование продуктов Microsoft в пользу открытого ПО. В качестве офисного пакета будет использован LibreOffice. Половина сотрудников будет переведена на LibreOffice в течение следующего месяца. Перевод всех сотрудников на открытое ПО планируют завершить до конца года.\nhttps://www.opennet.ru/opennews/art.shtml?num=63398\n","permalink":"https://ihadtoinstalllinux.github.io/posts/news/","summary":"Каролина Стейдж (Caroline Stage), министр по цифровизации в правительстве Дании, подтвердила согласование между правительством и региональными властями стратегии цифрового суверенитета. На первом этапе воплощения новой стратегии в жизнь Министерство цифровизации Дании прекратит использование продуктов Microsoft в пользу открытого ПО. В качестве офисного пакета будет использован LibreOffice. Половина сотрудников будет переведена на LibreOffice в течение следующего месяца. Перевод всех сотрудников на открытое ПО планируют завершить до конца года.\nhttps://www.opennet.ru/opennews/art.shtml?num=63398","title":"Госучреждения Дании уходят от продуктов Microsoft в пользу открытого ПО"},{"content":"vk: https://vk.com/ihadtoinstalllinux\ntelegram: https://t.me/ihadtoinstalllinux\n","permalink":"https://ihadtoinstalllinux.github.io/posts/about/","summary":"vk: https://vk.com/ihadtoinstalllinux\ntelegram: https://t.me/ihadtoinstalllinux","title":"About Us"}]