[{"content":"Доступен выпуск проекта TinyUSB 0.19, развивающего кроссплатформенный USB-стек для встраиваемых систем. Предоставляются компоненты USB-стека для USB-хостов (USB Host) и для подключаемых устройств (USB Device). Код проекта написан на языке Си и распространяется под лицензией MIT.\nhttps://www.opennet.ru/opennews/art.shtml?num=64005\n","permalink":"https://ihadtoinstalllinux.github.io/posts/news/","summary":"Доступен выпуск проекта TinyUSB 0.19, развивающего кроссплатформенный USB-стек для встраиваемых систем. Предоставляются компоненты USB-стека для USB-хостов (USB Host) и для подключаемых устройств (USB Device). Код проекта написан на языке Си и распространяется под лицензией MIT.\nhttps://www.opennet.ru/opennews/art.shtml?num=64005","title":"Опубликован открытый USB-стек TinyUSB 0.19"},{"content":"vk: https://vk.com/ihadtoinstalllinux\ntelegram: https://t.me/ihadtoinstalllinux\n","permalink":"https://ihadtoinstalllinux.github.io/posts/about/","summary":"vk: https://vk.com/ihadtoinstalllinux\ntelegram: https://t.me/ihadtoinstalllinux","title":"About Us"}]