[{"content":"Комитет FESCo (Fedora Engineering Steering Committee), отвечающий за техническую часть разработки дистрибутива Fedora Linux, утвердил переход на пакетный менеджер RPM 6 в осеннем выпуске Fedora 43. Релиз RPM 6.0 намечен на 3 квартал 2025 года.\nhttps://www.opennet.ru/opennews/art.shtml?num=63002\n","permalink":"https://ihadtoinstalllinux.github.io/posts/news/","summary":"Комитет FESCo (Fedora Engineering Steering Committee), отвечающий за техническую часть разработки дистрибутива Fedora Linux, утвердил переход на пакетный менеджер RPM 6 в осеннем выпуске Fedora 43. Релиз RPM 6.0 намечен на 3 квартал 2025 года.\nhttps://www.opennet.ru/opennews/art.shtml?num=63002","title":"Утверждён переход Fedora 43 на пакетный менеджер RPM 6. Смена лидера Fedora"},{"content":"vk: https://vk.com/ihadtoinstalllinux\ntelegram: https://t.me/ihadtoinstalllinux\n","permalink":"https://ihadtoinstalllinux.github.io/posts/about/","summary":"vk: https://vk.com/ihadtoinstalllinux\ntelegram: https://t.me/ihadtoinstalllinux","title":"About Us"}]