[{"content":"В кодовую базу, на основе которой формируется релиз GNOME 50, принят набор изменений с реализацией возможности восстановления приложений, запущенных в прошлом сеансе. В менеджер сеансов gnome-session добавлен режим для сохранения списка запущенных приложений во время завершения сеанса и восстановления их окон (запуска приложений) в последующем сеансе. В конфигуратор добавлен соответствующий переключатель, позволяющий отключить данное поведение.\nhttps://www.opennet.ru/opennews/art.shtml?num=64383\n","permalink":"https://ihadtoinstalllinux.github.io/posts/news/","summary":"В кодовую базу, на основе которой формируется релиз GNOME 50, принят набор изменений с реализацией возможности восстановления приложений, запущенных в прошлом сеансе. В менеджер сеансов gnome-session добавлен режим для сохранения списка запущенных приложений во время завершения сеанса и восстановления их окон (запуска приложений) в последующем сеансе. В конфигуратор добавлен соответствующий переключатель, позволяющий отключить данное поведение.\nhttps://www.opennet.ru/opennews/art.shtml?num=64383","title":"В GNOME реализовали восстановление приложений, запущенных до закрытия сеанса"},{"content":"vk: https://vk.com/ihadtoinstalllinux\ntelegram: https://t.me/ihadtoinstalllinux\n","permalink":"https://ihadtoinstalllinux.github.io/posts/about/","summary":"vk: https://vk.com/ihadtoinstalllinux\ntelegram: https://t.me/ihadtoinstalllinux","title":"About Us"}]