[{"content":"Сформировано пятое корректирующее обновление дистрибутива Debian 13, в которое включены накопившиеся обновления пакетов и добавлены исправления в инсталлятор. Выпуск включает 144 обновления с устранением проблем со стабильностью и 103 обновления с устранением уязвимостей. Из изменений в Debian 13.5 можно отметить обновление до свежих стабильных версий пакетов apache2, openssl и systemd. Удалён пакет dav4tbsync, функциональность которого теперь доступна в Thunderbird 140.\nhttps://www.opennet.ru/opennews/art.shtml?num=65462\n","permalink":"https://ihadtoinstalllinux.github.io/posts/news/","summary":"Сформировано пятое корректирующее обновление дистрибутива Debian 13, в которое включены накопившиеся обновления пакетов и добавлены исправления в инсталлятор. Выпуск включает 144 обновления с устранением проблем со стабильностью и 103 обновления с устранением уязвимостей. Из изменений в Debian 13.5 можно отметить обновление до свежих стабильных версий пакетов apache2, openssl и systemd. Удалён пакет dav4tbsync, функциональность которого теперь доступна в Thunderbird 140.\nhttps://www.opennet.ru/opennews/art.shtml?num=65462","title":"Новые версии Debian 12.14 и 13.5"},{"content":"vk: https://vk.com/ihadtoinstalllinux\ntelegram: https://t.me/ihadtoinstalllinux\n","permalink":"https://ihadtoinstalllinux.github.io/posts/about/","summary":"vk: https://vk.com/ihadtoinstalllinux\ntelegram: https://t.me/ihadtoinstalllinux","title":"About Us"}]