[{"content":"Компания Oracle опубликовала корректирующий релиз системы виртуализации VirtualBox 7.2.10, в котором представлено 14 изменений.\nhttps://www.opennet.ru/opennews/art.shtml?num=65702\n","permalink":"https://ihadtoinstalllinux.github.io/posts/news/","summary":"Компания Oracle опубликовала корректирующий релиз системы виртуализации VirtualBox 7.2.10, в котором представлено 14 изменений.\nhttps://www.opennet.ru/opennews/art.shtml?num=65702","title":"Выпуск VirtualBox 7.2.10"},{"content":"vk: https://vk.com/ihadtoinstalllinux\ntelegram: https://t.me/ihadtoinstalllinux\n","permalink":"https://ihadtoinstalllinux.github.io/posts/about/","summary":"vk: https://vk.com/ihadtoinstalllinux\ntelegram: https://t.me/ihadtoinstalllinux","title":"About Us"}]