[{"content":"Намджэ Чон (Namjae Jeon), участник проекта Samba, сопровождающий драйвер EXFAT и сервер KSMBD в ядре Linux, предложил включить в ядро новую реализацию файловой системы NTFS - ntfsplus. Предполагается, что более качественный и сопровождаемый NTFS-драйвер позволит улучшить совместимость Linux-систем с Windows-устройствами и упростить работу пользователей.\nhttps://www.opennet.ru/opennews/art.shtml?num=64084\n","permalink":"https://ihadtoinstalllinux.github.io/posts/news/","summary":"Намджэ Чон (Namjae Jeon), участник проекта Samba, сопровождающий драйвер EXFAT и сервер KSMBD в ядре Linux, предложил включить в ядро новую реализацию файловой системы NTFS - ntfsplus. Предполагается, что более качественный и сопровождаемый NTFS-драйвер позволит улучшить совместимость Linux-систем с Windows-устройствами и упростить работу пользователей.\nhttps://www.opennet.ru/opennews/art.shtml?num=64084","title":"Для ядра Linux предложен драйвер ntfsplus с новой реализацией NTFS"},{"content":"vk: https://vk.com/ihadtoinstalllinux\ntelegram: https://t.me/ihadtoinstalllinux\n","permalink":"https://ihadtoinstalllinux.github.io/posts/about/","summary":"vk: https://vk.com/ihadtoinstalllinux\ntelegram: https://t.me/ihadtoinstalllinux","title":"About Us"}]