[{"content":"Представлен выпуск пакета wayland-protocols 1.49, содержащего набор протоколов и расширений, дополняющих базовый протокол Wayland и предоставляющих возможности, необходимые для построения композитных серверов и пользовательских окружений.\nhttps://www.opennet.ru/opennews/art.shtml?num=65638\n","permalink":"https://ihadtoinstalllinux.github.io/posts/news/","summary":"Представлен выпуск пакета wayland-protocols 1.49, содержащего набор протоколов и расширений, дополняющих базовый протокол Wayland и предоставляющих возможности, необходимые для построения композитных серверов и пользовательских окружений.\nhttps://www.opennet.ru/opennews/art.shtml?num=65638","title":"Выпуск Wayland-Protocols 1.49"},{"content":"vk: https://vk.com/ihadtoinstalllinux\ntelegram: https://t.me/ihadtoinstalllinux\n","permalink":"https://ihadtoinstalllinux.github.io/posts/about/","summary":"vk: https://vk.com/ihadtoinstalllinux\ntelegram: https://t.me/ihadtoinstalllinux","title":"About Us"}]