[{"content":"«Базальт СПО» выпустила операционную систему «Альт Виртуализация» на 11 платформе.\nhttps://www.basealt.ru/about/news/archive/view/alt-virtualizacija-110-bystraja-ustanovka-podderzhka-sdn-obnovlenie-cherez-veb-interfeis-prostaja-migracija-iz-vmware\n","permalink":"https://ihadtoinstalllinux.github.io/posts/news/","summary":"«Базальт СПО» выпустила операционную систему «Альт Виртуализация» на 11 платформе.\nhttps://www.basealt.ru/about/news/archive/view/alt-virtualizacija-110-bystraja-ustanovka-podderzhka-sdn-obnovlenie-cherez-veb-interfeis-prostaja-migracija-iz-vmware","title":"«Альт Виртуализация» 11.0: быстрая установка, поддержка SDN, обновление через веб-интерфейс, простая миграция из VMware"},{"content":"vk: https://vk.com/ihadtoinstalllinux\ntelegram: https://t.me/ihadtoinstalllinux\n","permalink":"https://ihadtoinstalllinux.github.io/posts/about/","summary":"vk: https://vk.com/ihadtoinstalllinux\ntelegram: https://t.me/ihadtoinstalllinux","title":"About Us"}]