[{"content":"После 8 месяцев разработки опубликован релиз свободного гипервизора Xen 4.21. В разработке нового выпуска приняли участие такие компании, как Amazon, Arm, EPAM Systems и AMD. Код проекта написан на языке Си и распространяется под лицензией GPLv2+. Разработка ведётся в составе организации Linux Foundation.\nhttps://www.opennet.ru/opennews/art.shtml?num=64285\n","permalink":"https://ihadtoinstalllinux.github.io/posts/news/","summary":"После 8 месяцев разработки опубликован релиз свободного гипервизора Xen 4.21. В разработке нового выпуска приняли участие такие компании, как Amazon, Arm, EPAM Systems и AMD. Код проекта написан на языке Си и распространяется под лицензией GPLv2+. Разработка ведётся в составе организации Linux Foundation.\nhttps://www.opennet.ru/opennews/art.shtml?num=64285","title":"Выпуск гипервизора Xen 4.21"},{"content":"vk: https://vk.com/ihadtoinstalllinux\ntelegram: https://t.me/ihadtoinstalllinux\n","permalink":"https://ihadtoinstalllinux.github.io/posts/about/","summary":"vk: https://vk.com/ihadtoinstalllinux\ntelegram: https://t.me/ihadtoinstalllinux","title":"About Us"}]